Workbook

Sheet Costeo
A1: Costeo del menú — costo por trago y margen · La Quinta Pata
A2: Menu costing. Edite precios en la columna D (azul). El costo viene de Especificaciones → Insumos → Lotes. Estado marca ítems >3 pts sobre el objetivo.
A4: Ítem | B4: Item (EN) | C4: Sección | D4: Precio menú ($) | E4: Precio neto sin ITBMS ($) | F4: Costo ($) | G4: Costo % | H4: Objetivo % | I4: Ganancia bruta ($) | J4: Precio para objetivo ($, redondeo 0.50) | K4: Estado
A5: Canal Mule | B5: Canal Mule | C5: De la casa | D5: 7 | E5: =IF(Ajustes!$B$11=1,D5/(1+Ajustes!$B$12),D5) -> 6.3636364 | F5: =SUMIF(Especificaciones!$A$5:$A$153,A5,Especificaciones!$G$5:$G$153) -> 1.1751746 | G5: =IFERROR(F5/E5,0) -> 0.18467029 | H5: =IFERROR(INDEX(Ajustes!$B$16:$B$22,MATCH(C5,Ajustes!$A$16:$A$22,0)),0.2) -> 0.2 | I5: =E5-F5 -> 5.1884618 | J5: =IFERROR(CEILING(F5/H5*IF(Ajustes!$B$11=1,1+Ajustes!$B$12,1),0.5),0) -> 6.5 | K5: =IF(G5>H5+0.03,"Reajustar precio / receta",IF(G5<H5-0.08,"Margen alto","OK")) -> OK
A6: Oaxaca Paloma | B6: Oaxaca Paloma | C6: De la casa | D6: 8 | E6: =IF(Ajustes!$B$11=1,D6/(1+Ajustes!$B$12),D6) -> 7.2727273 | F6: =SUMIF(Especificaciones!$A$5:$A$153,A6,Especificaciones!$G$5:$G$153) -> 1.728675 | G6: =IFERROR(F6/E6,0) -> 0.23769281 | H6: =IFERROR(INDEX(Ajustes!$B$16:$B$22,MATCH(C6,Ajustes!$A$16:$A$22,0)),0.2) -> 0.2 | I6: =E6-F6 -> 5.5440523 | J6: =IFERROR(CEILING(F6/H6*IF(Ajustes!$B$11=1,1+Ajustes!$B$12,1),0.5),0) -> 10 | K6: =IF(G6>H6+0.03,"Reajustar precio / receta",IF(G6<H6-0.08,"Margen alto","OK")) -> Reajustar precio / receta
A7: Havana Maracuyá | B7: Havana Maracuyá | C7: De la casa | D7: 8 | E7: =IF(Ajustes!$B$11=1,D7/(1+Ajustes!$B$12),D7) -> 7.2727273 | F7: =SUMIF(Especificaciones!$A$5:$A$153,A7,Especificaciones!$G$5:$G$153) -> 1.0508845 | G7: =IFERROR(F7/E7,0) -> 0.14449661 | H7: =IFERROR(INDEX(Ajustes!$B$16:$B$22,MATCH(C7,Ajustes!$A$16:$A$22,0)),0.2) -> 0.2 | I7: =E7-F7 -> 6.2218428 | J7: =IFERROR(CEILING(F7/H7*IF(Ajustes!$B$11=1,1+Ajustes!$B$12,1),0.5),0) -> 6 | K7: =IF(G7>H7+0.03,"Reajustar precio / receta",IF(G7<H7-0.08,"Margen alto","OK")) -> OK
A8: Lima Chilcano | B8: Lima Chilcano | C8: De la casa | D8: 8 | E8: =IF(Ajustes!$B$11=1,D8/(1+Ajustes!$B$12),D8) -> 7.2727273 | F8: =SUMIF(Especificaciones!$A$5:$A$153,A8,Especificaciones!$G$5:$G$153) -> 1.8491379 | G8: =IFERROR(F8/E8,0) -> 0.25425647 | H8: =IFERROR(INDEX(Ajustes!$B$16:$B$22,MATCH(C8,Ajustes!$A$16:$A$22,0)),0.2) -> 0.2 | I8: =E8-F8 -> 5.4235893 | J8: =IFERROR(CEILING(F8/H8*IF(Ajustes!$B$11=1,1+Ajustes!$B$12,1),0.5),0) -> 10.5 | K8: =IF(G8>H8+0.03,"Reajustar precio / receta",IF(G8<H8-0.08,"Margen alto","OK")) -> Reajustar precio / receta
A9: Lisboa Spritz | B9: Lisboa Spritz | C9: De la casa | D9: 8 | E9: =IF(Ajustes!$B$11=1,D9/(1+Ajustes!$B$12),D9) -> 7.2727273 | F9: =SUMIF(Especificaciones!$A$5:$A$153,A9,Especificaciones!$G$5:$G$153) -> 1.8551262 | G9: =IFERROR(F9/E9,0) -> 0.25507985 | H9: =IFERROR(INDEX(Ajustes!$B$16:$B$22,MATCH(C9,Ajustes!$A$16:$A$22,0)),0.2) -> 0.2 | I9: =E9-F9 -> 5.4176011 | J9: =IFERROR(CEILING(F9/H9*IF(Ajustes!$B$11=1,1+Ajustes!$B$12,1),0.5),0) -> 10.5 | K9: =IF(G9>H9+0.03,"Reajustar precio / receta",IF(G9<H9-0.08,"Margen alto","OK")) -> Reajustar precio / receta
A10: Bangkok Smash | B10: Bangkok Smash | C10: De la casa | D10: 8 | E10: =IF(Ajustes!$B$11=1,D10/(1+Ajustes!$B$12),D10) -> 7.2727273 | F10: =SUMIF(Especificaciones!$A$5:$A$153,A10,Especificaciones!$G$5:$G$153) -> 1.0118092 | G10: =IFERROR(F10/E10,0) -> 0.13912376 | H10: =IFERROR(INDEX(Ajustes!$B$16:$B$22,MATCH(C10,Ajustes!$A$16:$A$22,0)),0.2) -> 0.2 | I10: =E10-F10 -> 6.2609181 | J10: =IFERROR(CEILING(F10/H10*IF(Ajustes!$B$11=1,1+Ajustes!$B$12,1),0.5),0) -> 6 | K10: =IF(G10>H10+0.03,"Reajustar precio / receta",IF(G10<H10-0.08,"Margen alto","OK")) -> OK
A11: Kyoto Highball | B11: Kyoto Highball | C11: De la casa | D11: 9 | E11: =IF(Ajustes!$B$11=1,D11/(1+Ajustes!$B$12),D11) -> 8.1818182 | F11: =SUMIF(Especificaciones!$A$5:$A$153,A11,Especificaciones!$G$5:$G$153) -> 1.7953205 | G11: =IFERROR(F11/E11,0) -> 0.21942807 | H11: =IFERROR(INDEX(Ajustes!$B$16:$B$22,MATCH(C11,Ajustes!$A$16:$A$22,0)),0.2) -> 0.2 | I11: =E11-F11 -> 6.3864976 | J11: =IFERROR(CEILING(F11/H11*IF(Ajustes!$B$11=1,1+Ajustes!$B$12,1),0.5),0) -> 10 | K11: =IF(G11>H11+0.03,"Reajustar precio / receta",IF(G11<H11-0.08,"Margen alto","OK")) -> OK
A12: Milano Sbagliato | B12: Milano Sbagliato | C12: De la casa | D12: 9 | E12: =IF(Ajustes!$B$11=1,D12/(1+Ajustes!$B$12),D12) -> 8.1818182 | F12: =SUMIF(Especificaciones!$A$5:$A$153,A12,Especificaciones!$G$5:$G$153) -> 2.111181 | G12: =IFERROR(F12/E12,0) -> 0.25803323 | H12: =IFERROR(INDEX(Ajustes!$B$16:$B$22,MATCH(C12,Ajustes!$A$16:$A$22,0)),0.2) -> 0.2 | I12: =E12-F12 -> 6.0706372 | J12: =IFERROR(CEILING(F12/H12*IF(Ajustes!$B$11=1,1+Ajustes!$B$12,1),0.5),0) -> 12 | K12: =IF(G12>H12+0.03,"Reajustar precio / receta",IF(G12<H12-0.08,"Margen alto","OK")) -> Reajustar precio / receta
A13: Margarita de limón | B13: Lime margarita | C13: Clásico | D13: 7 | E13: =IF(Ajustes!$B$11=1,D13/(1+Ajustes!$B$12),D13) -> 6.3636364 | F13: =SUMIF(Especificaciones!$A$5:$A$153,A13,Especificaciones!$G$5:$G$153) -> 1.6412588 | G13: =IFERROR(F13/E13,0) -> 0.2579121 | H13: =IFERROR(INDEX(Ajustes!$B$16:$B$22,MATCH(C13,Ajustes!$A$16:$A$22,0)),0.2) -> 0.2 | I13: =E13-F13 -> 4.7223776 | J13: =IFERROR(CEILING(F13/H13*IF(Ajustes!$B$11=1,1+Ajustes!$B$12,1),0.5),0) -> 9.5 | K13: =IF(G13>H13+0.03,"Reajustar precio / receta",IF(G13<H13-0.08,"Margen alto","OK")) -> Reajustar precio / receta
A14: Margarita de maracuyá | B14: Passion fruit margarita | C14: Clásico | D14: 7 | E14: =IF(Ajustes!$B$11=1,D14/(1+Ajustes!$B$12),D14) -> 6.3636364 | F14: =SUMIF(Especificaciones!$A$5:$A$153,A14,Especificaciones!$G$5:$G$153) -> 1.6643531 | G14: =IFERROR(F14/E14,0) -> 0.2615412 | H14: =IFERROR(INDEX(Ajustes!$B$16:$B$22,MATCH(C14,Ajustes!$A$16:$A$22,0)),0.2) -> 0.2 | I14: =E14-F14 -> 4.6992832 | J14: =IFERROR(CEILING(F14/H14*IF(Ajustes!$B$11=1,1+Ajustes!$B$12,1),0.5),0) -> 9.5 | K14: =IF(G14>H14+0.03,"Reajustar precio / receta",IF(G14<H14-0.08,"Margen alto","OK")) -> Reajustar precio / receta
A15: Margarita de flor de Jamaica | B15: Hibiscus margarita | C15: Clásico | D15: 9 | E15: =IF(Ajustes!$B$11=1,D15/(1+Ajustes!$B$12),D15) -> 8.1818182 | F15: =SUMIF(Especificaciones!$A$5:$A$153,A15,Especificaciones!$G$5:$G$153) -> 1.6337068 | G15: =IFERROR(F15/E15,0) -> 0.19967527 | H15: =IFERROR(INDEX(Ajustes!$B$16:$B$22,MATCH(C15,Ajustes!$A$16:$A$22,0)),0.2) -> 0.2 | I15: =E15-F15 -> 6.5481114 | J15: =IFERROR(CEILING(F15/H15*IF(Ajustes!$B$11=1,1+Ajustes!$B$12,1),0.5),0) -> 9 | K15: =IF(G15>H15+0.03,"Reajustar precio / receta",IF(G15<H15-0.08,"Margen alto","OK")) -> OK
A16: Mojito de limón | B16: Lime mojito | C16: Clásico | D16: 7 | E16: =IF(Ajustes!$B$11=1,D16/(1+Ajustes!$B$12),D16) -> 6.3636364 | F16: =SUMIF(Especificaciones!$A$5:$A$153,A16,Especificaciones!$G$5:$G$153) -> 0.91022564 | G16: =IFERROR(F16/E16,0) -> 0.14303546 | H16: =IFERROR(INDEX(Ajustes!$B$16:$B$22,MATCH(C16,Ajustes!$A$16:$A$22,0)),0.2) -> 0.2 | I16: =E16-F16 -> 5.4534107 | J16: =IFERROR(CEILING(F16/H16*IF(Ajustes!$B$11=1,1+Ajustes!$B$12,1),0.5),0) -> 5.5 | K16: =IF(G16>H16+0.03,"Reajustar precio / receta",IF(G16<H16-0.08,"Margen alto","OK")) -> OK
... A59: Carajillo | B59: Carajillo | C59: Café | D59: 7 | E59: =IF(Ajustes!$B$11=1,D59/(1+Ajustes!$B$12),D59) -> 6.3636364 | F59: =SUMIF(Especificaciones!$A$5:$A$153,A59,Especificaciones!$G$5:$G$153) -> 2.0978549 | G59: =IFERROR(F59/E59,0) -> 0.32966291 | H59: =IFERROR(INDEX(Ajustes!$B$16:$B$22,MATCH(C59,Ajustes!$A$16:$A$22,0)),0.2) -> 0.15 | I59: =E59-F59 -> 4.2657815 | J59: =IFERROR(CEILING(F59/H59*IF(Ajustes!$B$11=1,1+Ajustes!$B$12,1),0.5),0) -> 15.5 | K59: =IF(G59>H59+0.03,"Reajustar precio / receta",IF(G59<H59-0.08,"Margen alto","OK")) -> Reajustar precio / receta
A61: Promedio por sección · Average by section
A62: Sección | B62: Section (EN) | F62: Costo prom. ($) | G62: Costo % prom. | H62: Objetivo % | I62: Ganancia prom. ($)
A63: De la casa | B63: Signature | F63: =IFERROR(AVERAGEIF($C$5:$C$59,A63,$F$5:$F$59),0) -> 1.5721636 | G63: =IFERROR(AVERAGEIF($C$5:$C$59,A63,$G$5:$G$59),0) -> 0.21159764 | H63: =IFERROR(INDEX(Ajustes!$B$16:$B$22,MATCH(A63,Ajustes!$A$16:$A$22,0)),0) -> 0.2 | I63: =IFERROR(AVERAGEIF($C$5:$C$59,A63,$I$5:$I$59),0) -> 5.8142
A64: Clásico | B64: Classic | F64: =IFERROR(AVERAGEIF($C$5:$C$59,A64,$F$5:$F$59),0) -> 1.4361844 | G64: =IFERROR(AVERAGEIF($C$5:$C$59,A64,$G$5:$G$59),0) -> 0.20892057 | H64: =IFERROR(INDEX(Ajustes!$B$16:$B$22,MATCH(A64,Ajustes!$A$16:$A$22,0)),0) -> 0.2 | I64: =IFERROR(AVERAGEIF($C$5:$C$59,A64,$I$5:$I$59),0) -> 5.3819975
A65: Cerveza | B65: Beer | F65: =IFERROR(AVERAGEIF($C$5:$C$59,A65,$F$5:$F$59),0) -> 1.8826667 | G65: =IFERROR(AVERAGEIF($C$5:$C$59,A65,$G$5:$G$59),0) -> 0.33699801 | H65: =IFERROR(INDEX(Ajustes!$B$16:$B$22,MATCH(A65,Ajustes!$A$16:$A$22,0)),0) -> 0.3 | I65: =IFERROR(AVERAGEIF($C$5:$C$59,A65,$I$5:$I$59),0) -> 3.2991515
A66: Vino | B66: Wine | F66: =IFERROR(AVERAGEIF($C$5:$C$59,A66,$F$5:$F$59),0) -> 5.3980422 | G66: =IFERROR(AVERAGEIF($C$5:$C$59,A66,$G$5:$G$59),0) -> 0.33755036 | H66: =IFERROR(INDEX(Ajustes!$B$16:$B$22,MATCH(A66,Ajustes!$A$16:$A$22,0)),0) -> 0.3 | I66: =IFERROR(AVERAGEIF($C$5:$C$59,A66,$I$5:$I$59),0) -> 9.5606355
A67: Destilados | B67: Spirits | F67: =IFERROR(AVERAGEIF($C$5:$C$59,A67,$F$5:$F$59),0) -> 1.3631104 | G67: =IFERROR(AVERAGEIF($C$5:$C$59,A67,$G$5:$G$59),0) -> 0.23890333 | H67: =IFERROR(INDEX(Ajustes!$B$16:$B$22,MATCH(A67,Ajustes!$A$16:$A$22,0)),0) -> 0.18 | I67: =IFERROR(AVERAGEIF($C$5:$C$59,A67,$I$5:$I$59),0) -> 4.0914351
A68: Sin alcohol | B68: Zero-proof | F68: =IFERROR(AVERAGEIF($C$5:$C$59,A68,$F$5:$F$59),0) -> 0.44520913 | G68: =IFERROR(AVERAGEIF($C$5:$C$59,A68,$G$5:$G$59),0) -> 0.14681584 | H68: =IFERROR(INDEX(Ajustes!$B$16:$B$22,MATCH(A68,Ajustes!$A$16:$A$22,0)),0) -> 0.15 | I68: =IFERROR(AVERAGEIF($C$5:$C$59,A68,$I$5:$I$59),0) -> 2.7366091
A69: Café | B69: Coffee | F69: =IFERROR(AVERAGEIF($C$5:$C$59,A69,$F$5:$F$59),0) -> 1.3289274 | G69: =IFERROR(AVERAGEIF($C$5:$C$59,A69,$G$5:$G$59),0) -> 0.28803146 | H69: =IFERROR(INDEX(Ajustes!$B$16:$B$22,MATCH(A69,Ajustes!$A$16:$A$22,0)),0) -> 0.15 | I69: =IFERROR(AVERAGEIF($C$5:$C$59,A69,$I$5:$I$59),0) -> 2.9892544
A71: Estados: OK · Reajustar precio / receta = over target (reprice / re-spec) · Margen alto = well under target, room to upgrade

Sheet Recetas
A1: Fichas de receta para bartenders — cócteles, sin alcohol y café
A2: Bartender spec cards. La receta refleja la hoja Especificaciones; si cambia cantidades allá, actualice el texto aquí.
A4: Bebida | B4: Drink (EN) | C4: Sección | D4: Vaso / copa | E4: Hielo | F4: Receta | G4: Método | H4: Method (EN) | I4: Guarnición
A5: Canal Mule | B5: Canal Mule | C5: De la casa | D5: Highball / taza de cobre | E5: Cubos | F5: 2 oz Seco Herrerano 0.5 oz Jugo de limón fresco 4 oz Ginger beer 2 golpes de Amargo de Angostura | G5: Construir sobre hielo, completar con ginger beer, amargo encima | H5: Build over ice, top ginger beer, float bitters | I5: Gajo de limón
A6: Oaxaca Paloma | B6: Oaxaca Paloma | C6: De la casa | D6: Highball, medio borde de sal | E6: Cubos | F6: 1.5 oz Tequila blanco 2 oz Jugo de toronja fresco 0.5 oz Jugo de limón fresco 0.25 oz Jarabe simple 1:1 2 oz Soda 1 × Borde de sal | G6: Construir tequila, jugos y jarabe, mezclar, completar con soda | H6: Build tequila + juices + syrup, stir, top soda | I6: Gajo de toronja
A7: Havana Maracuyá | B7: Havana Maracuyá | C7: De la casa | D7: Highball | E7: Frappé | F7: 2 oz Ron blanco 1 oz Pulpa de maracuyá 0.75 oz Jugo de limón fresco 0.5 oz Jarabe simple 1:1 1 × Ramita de hierbabuena 2 oz Soda | G7: Macerar suave la hierbabuena con jarabe, añadir ron, pulpa y limón, batir con cuchara, completar con soda | H7: Lightly muddle mint + syrup, add rum/pulp/lime, churn, top soda | I7: Ramita de hierbabuena
A8: Lima Chilcano | B8: Lima Chilcano | C8: De la casa | D8: Highball | E8: Cubos | F8: 2 oz Pisco 0.5 oz Jugo de limón fresco 4 oz Ginger ale 2 golpes de Amargo de Angostura | G8: Construir pisco y limón, completar con ginger ale, amargo encima | H8: Build pisco + lime, top ginger ale, bitters on top | I8: Rueda de limón
A9: Lisboa Spritz | B9: Lisboa Spritz | C9: De la casa | D9: Copa de vino | E9: Cubos | F9: 2.5 oz Oporto blanco 3 oz Agua tónica 1 × Rueda de naranja 1 × Ramita de hierbabuena | G9: Oporto sobre hielo, completar con tónica, mezclar suave | H9: Build port over ice, top tonic, gentle stir | I9: Rueda de naranja + hierbabuena
A10: Bangkok Smash | B10: Bangkok Smash | C10: De la casa | D10: Rocks | E10: Frappé | F10: 2 oz Vodka 0.75 oz Jarabe de hierba de limón y jengibre 0.75 oz Jugo de limón fresco 1 × Ramita de albahaca tailandesa | G10: Agitar fuerte con la albahaca, doble colado sobre hielo frappé | H10: Shake hard with basil, double strain over crushed ice | I10: Ramita de albahaca
A11: Kyoto Highball | B11: Kyoto Highball | C11: De la casa | D11: Highball alto (frío) | E11: Lanza / cubos | F11: 2 oz Whisky 0.5 oz Jarabe de jengibre y miel 0.5 oz Jugo de limón amarillo 4 oz Soda | G11: Mezclar whisky, jarabe y limón amarillo en hielo 10 seg, completar con soda muy fría, una sola vuelta | H11: Stir whisky + syrup + lemon 10 sec, top very cold soda, one lift | I11: Twist de limón amarillo
A12: Milano Sbagliato | B12: Milano Sbagliato | C12: De la casa | D12: Rocks / copa de vino | E12: Cubo grande | F12: 1 oz Campari 1 oz Vermut rojo 2 oz Prosecco 1 × Rueda de naranja | G12: Construir Campari y vermut, mezclar, completar con prosecco | H12: Build Campari + vermouth, stir, top prosecco | I12: Rueda de naranja
A13: Margarita de limón | B13: Lime margarita | C13: Clásico | D13: Rocks, borde de sal | E13: Cubos | F13: 1.5 oz Tequila blanco 0.75 oz Triple sec 1 oz Jugo de limón fresco 0.25 oz Jarabe simple 1:1 1 × Borde de sal | G13: Agitar, colar sobre hielo nuevo | H13: Shake, strain over fresh ice | I13: Rueda de limón
A14: Margarita de maracuyá | B14: Passion fruit margarita | C14: Clásico | D14: Rocks, borde de sal | E14: Cubos | F14: 1.5 oz Tequila blanco 0.5 oz Triple sec 1 oz Pulpa de maracuyá 0.75 oz Jugo de limón fresco 0.25 oz Jarabe simple 1:1 1 × Borde de sal | G14: Agitar fuerte, colar sobre hielo nuevo | H14: Shake hard, strain over fresh ice | I14: Media maracuyá o rueda de limón
A15: Margarita de flor de Jamaica | B15: Hibiscus margarita | C15: Clásico | D15: Rocks, borde de sal | E15: Cubos | F15: 1.5 oz Tequila blanco 0.5 oz Triple sec 1 oz Jarabe de saril 1 oz Jugo de limón fresco 1 × Borde de sal | G15: Agitar, colar sobre hielo nuevo. Usa el mismo jarabe de saril (flor de Jamaica) del Saril Cooler | H15: Shake, strain over fresh ice. Uses the same saril (hibiscus) syrup as the Saril Cooler | I15: Flor de Jamaica deshidratada
... A36: Carajillo | B36: Carajillo | C36: Café | D36: Rocks | E36: Cubos | F36: 1 × Shot de espresso (café de Boquete) 1.5 oz Licor 43 | G36: Agitar fuerte espresso y Licor 43, colar sobre hielo | H36: Shake espresso + Licor 43 hard, strain over ice | I36: —

Sheet Ajustes
A1: Programa de bebidas — Ajustes y leyenda
A2: Drink program — Settings & legend
A4: Leyenda · Legend
A5: Texto azul = dato que usted edita · Blue = input you edit
A6: Texto negro = fórmula, no sobrescribir · Black = formula, don't overwrite
A7: Texto verde = viene de otra hoja · Green = pulled from another sheet
A8: Fondo amarillo = supuesto a verificar (cotización / contador) · Yellow = assumption to verify
A10: Impuesto · Tax
A11: ¿Precios del menú incluyen ITBMS? (1 = sí, 0 = no) · Menu prices include ITBMS? | B11: 1
A12: Tasa ITBMS bebidas alcohólicas · ITBMS rate, alcoholic drinks | B12: 0.1 | C12: Supuesto — confirme la tasa vigente con su contador; bebidas sin alcohol pueden diferir. · Assumption — confirm with your accountant.
A14: Costo objetivo por sección · Target cost by section
A15: Sección · Section | B15: Objetivo % · Target % | C15: Nota · Note
A16: De la casa | B16: 0.2 | C16: Signature · Nivel casual: 18–22%
A17: Clásico | B17: 0.2 | C17: Classic
A18: Cerveza | B18: 0.3 | C18: Beer · Botella corre más alto · Bottled runs higher
A19: Vino | B19: 0.3 | C19: Wine · Por copa; botellas ~35–40% · By the glass
A20: Destilados | B20: 0.18 | C20: Spirits · Tragos solos · Neat pours
A21: Sin alcohol | B21: 0.15 | C21: Zero-proof
A22: Café | B22: 0.15 | C22: Coffee

Sheet Insumos
A1: Lista de precios de insumos — reemplace las celdas amarillas con cotizaciones de su proveedor
A2: Ingredient price list. Ejemplo: Seco Herrerano, botella 1 L = 33.8 oz a $8.00 → $0.237/oz. Precios estimados para Ciudad de Panamá, no cotizaciones.
A4: Insumo | B4: Ingredient (EN) | C4: Categoría | D4: Presentación de compra | E4: Unidades por compra | F4: Unidad | G4: Costo de compra | H4: Costo por unidad
A5: Seco Herrerano | B5: Seco Herrerano | C5: Destilado | D5: Botella 1 L | E5: 33.8 | F5: oz | G5: 8 | H5: =IFERROR(G5/E5,0) -> 0.23668639
A6: Ron blanco | B6: White rum | C6: Destilado | D6: Botella 1 L | E6: 33.8 | F6: oz | G6: 10 | H6: =IFERROR(G6/E6,0) -> 0.29585799
A7: Ron añejo panameño | B7: Panamanian aged rum | C7: Destilado | D7: Botella 750 ml | E7: 25.36 | F7: oz | G7: 18 | H7: =IFERROR(G7/E7,0) -> 0.70977918
A8: Vodka | B8: Vodka | C8: Destilado | D8: Botella 1 L | E8: 33.8 | F8: oz | G8: 12 | H8: =IFERROR(G8/E8,0) -> 0.35502959
A9: Ginebra | B9: Gin | C9: Destilado | D9: Botella 750 ml | E9: 25.36 | F9: oz | G9: 16 | H9: =IFERROR(G9/E9,0) -> 0.63091483
A10: Tequila blanco | B10: Tequila blanco | C10: Destilado | D10: Botella 750 ml | E10: 25.36 | F10: oz | G10: 20 | H10: =IFERROR(G10/E10,0) -> 0.78864353
A11: Mezcal | B11: Mezcal | C11: Destilado | D11: Botella 750 ml | E11: 25.36 | F11: oz | G11: 32 | H11: =IFERROR(G11/E11,0) -> 1.2618297
A12: Pisco | B12: Pisco | C12: Destilado | D12: Botella 750 ml | E12: 25.36 | F12: oz | G12: 18 | H12: =IFERROR(G12/E12,0) -> 0.70977918
A13: Cachaça | B13: Cachaça | C13: Destilado | D13: Botella 750 ml | E13: 25.36 | F13: oz | G13: 18 | H13: =IFERROR(G13/E13,0) -> 0.70977918
A14: Whisky | B14: Whisky | C14: Destilado | D14: Botella 750 ml | E14: 25.36 | F14: oz | G14: 18 | H14: =IFERROR(G14/E14,0) -> 0.70977918
A15: Bourbon | B15: Bourbon | C15: Destilado | D15: Botella 750 ml | E15: 25.36 | F15: oz | G15: 22 | H15: =IFERROR(G15/E15,0) -> 0.86750789
A16: Triple sec | B16: Triple sec | C16: Licor | D16: Botella 1 L | E16: 33.8 | F16: oz | G16: 10 | H16: =IFERROR(G16/E16,0) -> 0.29585799
... A52: Shot de espresso (café de Boquete) | B52: Espresso shot (Boquete beans) | C52: Café | D52: 1 lb de grano (~25 shots) | E52: 25 | F52: unidad | G52: 14 | H52: =IFERROR(G52/E52,0) -> 0.56
A53: Jarabe simple 1:1 | B53: Simple syrup 1:1 | C53: Lote de la casa | D53: Ver hoja Lotes | F53: oz | H53: =Lotes!$F$9 -> 0.0256
A54: Jarabe de jengibre y miel | B54: Ginger-honey syrup | C54: Lote de la casa | D54: Ver hoja Lotes | F54: oz | H54: =Lotes!$F$16 -> 0.25428571
A55: Jarabe de hierba de limón y jengibre | B55: Lemongrass-ginger syrup | C55: Lote de la casa | D55: Ver hoja Lotes | F55: oz | H55: =Lotes!$F$24 -> 0.069
A56: Jarabe de saril | B56: Saril syrup | C56: Lote de la casa | D56: Ver hoja Lotes | F56: oz | H56: =Lotes!$F$33 -> 0.0728125
A57: Chicha de piña | B57: Pineapple chicha | C57: Lote de la casa | D57: Ver hoja Lotes | F57: oz | H57: =Lotes!$F$41 -> 0.028

Sheet Lotes
A1: Recetas de lote de la casa — costo por oz alimenta Insumos
A2: House batch recipes — cost per oz feeds Insumos
A4: Lote · Batch | B4: Ingrediente | C4: Cant. · Qty | D4: Unidad | E4: Costo / unidad | F4: Costo línea | G4: Método y vida útil · Method & shelf life
A5: Jarabe simple 1:1 | B5: Azúcar blanca | C5: 32 | D5: oz | E5: 0.04 | F5: =C5*E5 -> 1.28 | G5: Disolver azúcar en agua caliente. Enfriar. 2 semanas refrigerado. · Dissolve, cool. 2 weeks refrigerated.
A6: Simple syrup 1:1 | B6: Agua | C6: 32 | D6: oz | E6: 0 | F6: =C6*E6 -> 0
B7: Costo del lote · Batch cost | F7: =SUM(F5:F6) -> 1.28
B8: Rendimiento (oz) · Yield | C8: 50 | G8: Estimado — mida su primer lote y actualice. · Estimate — measure first batch.
B9: Costo por oz · Cost per oz | F9: =IFERROR(F7/C8,0) -> 0.0256
A11: Jarabe de jengibre y miel | B11: Miel | C11: 16 | D11: oz | E11: 0.4 | F11: =C11*E11 -> 6.4 | G11: Hervir jengibre en agua 10 min, colar, batir la miel fuera del fuego. 2 semanas. · Simmer ginger 10 min, strain, whisk in honey off heat. 2 weeks.
A12: Ginger-honey syrup | B12: Jengibre fresco, en rodajas | C12: 6 | D12: oz | E12: 0.12 | F12: =C12*E12 -> 0.72
A13: Jarabe de jengibre y miel | B13: Agua | C13: 12 | D13: oz | E13: 0 | F13: =C13*E13 -> 0
B14: Costo del lote · Batch cost | F14: =SUM(F11:F13) -> 7.12
B15: Rendimiento (oz) · Yield | C15: 28 | G15: Estimado — mida su primer lote y actualice. · Estimate — measure first batch.
B16: Costo por oz · Cost per oz | F16: =IFERROR(F14/C15,0) -> 0.25428571
A18: Jarabe de hierba de limón y jengibre | B18: Azúcar blanca | C18: 32 | D18: oz | E18: 0.04 | F18: =C18*E18 -> 1.28 | G18: Machacar la hierba de limón, hervir todo 15 min, reposar 30 min, colar. 10 días. · Bruise, simmer 15 min, steep 30, strain. 10 days.
A19: Lemongrass-ginger syrup | B19: Agua | C19: 32 | D19: oz | E19: 0 | F19: =C19*E19 -> 0
A20: Jarabe de hierba de limón y jengibre | B20: Tallo de hierba de limón | C20: 4 | D20: unidad | E20: 0.25 | F20: =C20*E20 -> 1
A21: Jarabe de hierba de limón y jengibre | B21: Jengibre fresco, en rodajas | C21: 4 | D21: oz | E21: 0.12 | F21: =C21*E21 -> 0.48
B22: Costo del lote · Batch cost | F22: =SUM(F18:F21) -> 2.76
B23: Rendimiento (oz) · Yield | C23: 40 | G23: Estimado — mida su primer lote y actualice. · Estimate — measure first batch.
B24: Costo por oz · Cost per oz | F24: =IFERROR(F22/C23,0) -> 0.069
A26: Jarabe de saril | B26: Saril seco | C26: 4 | D26: oz | E26: 0.6 | F26: =C26*E26 -> 2.4 | G26: Hervir 20 min, reposar toda la noche, colar. 10 días. · Simmer 20 min, steep overnight, strain. 10 days.
A27: Saril syrup | B27: Azúcar blanca | C27: 32 | D27: oz | E27: 0.04 | F27: =C27*E27 -> 1.28
A28: Jarabe de saril | B28: Jengibre fresco, en rodajas | C28: 4 | D28: oz | E28: 0.12 | F28: =C28*E28 -> 0.48
A29: Jarabe de saril | B29: Clavo y canela | C29: 1 | D29: unidad | E29: 0.5 | F29: =C29*E29 -> 0.5
A30: Jarabe de saril | B30: Agua | C30: 48 | D30: oz | E30: 0 | F30: =C30*E30 -> 0
B31: Costo del lote · Batch cost | F31: =SUM(F26:F30) -> 4.66
B32: Rendimiento (oz) · Yield | C32: 64 | G32: Estimado — mida su primer lote y actualice. · Estimate — measure first batch.
B33: Costo por oz · Cost per oz | F33: =IFERROR(F31/C32,0) -> 0.0728125
A35: Chicha de piña | B35: Piña (cáscara y corazón) | C35: 1 | D35: unidad | E35: 1.5 | F35: =C35*E35 -> 1.5 | G35: Reposar cáscara con especias 24–48 h a temperatura ambiente, colar, endulzar, enfriar. 4 días. · Steep 24–48h, strain, sweeten, chill. 4 days.
A36: Pineapple chicha | B36: Azúcar morena | C36: 16 | D36: oz | E36: 0.05 | F36: =C36*E36 -> 0.8
A37: Chicha de piña | B37: Clavo y canela | C37: 1 | D37: unidad | E37: 0.5 | F37: =C37*E37 -> 0.5
A38: Chicha de piña | B38: Agua | C38: 96 | D38: oz | E38: 0 | F38: =C38*E38 -> 0
B39: Costo del lote · Batch cost | F39: =SUM(F35:F38) -> 2.8
B40: Rendimiento (oz) · Yield | C40: 100 | G40: Estimado — mida su primer lote y actualice. · Estimate — measure first batch.
B41: Costo por oz · Cost per oz | F41: =IFERROR(F39/C40,0) -> 0.028

Sheet Especificaciones
A1: Líneas de receta — una fila por ingrediente (alimenta todos los costos)
A2: Recipe lines — one row per ingredient (drives all costs)
A4: Bebida | B4: Drink (EN) | C4: Ingrediente | D4: Cant. · Qty | E4: Unidad | F4: Costo / unidad | G4: Costo línea
A5: Canal Mule | B5: Canal Mule | C5: Seco Herrerano | D5: 2 | E5: =IFERROR(INDEX(Insumos!$F$5:$F$57,MATCH(C5,Insumos!$A$5:$A$57,0)),"?") -> oz | F5: =IFERROR(INDEX(Insumos!$H$5:$H$57,MATCH(C5,Insumos!$A$5:$A$57,0)),0) -> 0.23668639 | G5: =D5*F5 -> 0.47337278
A6: Canal Mule | B6: Canal Mule | C6: Jugo de limón fresco | D6: 0.5 | E6: =IFERROR(INDEX(Insumos!$F$5:$F$57,MATCH(C6,Insumos!$A$5:$A$57,0)),"?") -> oz | F6: =IFERROR(INDEX(Insumos!$H$5:$H$57,MATCH(C6,Insumos!$A$5:$A$57,0)),0) -> 0.2 | G6: =D6*F6 -> 0.1
A7: Canal Mule | B7: Canal Mule | C7: Ginger beer | D7: 4 | E7: =IFERROR(INDEX(Insumos!$F$5:$F$57,MATCH(C7,Insumos!$A$5:$A$57,0)),"?") -> oz | F7: =IFERROR(INDEX(Insumos!$H$5:$H$57,MATCH(C7,Insumos!$A$5:$A$57,0)),0) -> 0.11666667 | G7: =D7*F7 -> 0.46666667
A8: Canal Mule | B8: Canal Mule | C8: Amargo de Angostura | D8: 2 | E8: =IFERROR(INDEX(Insumos!$F$5:$F$57,MATCH(C8,Insumos!$A$5:$A$57,0)),"?") -> golpe | F8: =IFERROR(INDEX(Insumos!$H$5:$H$57,MATCH(C8,Insumos!$A$5:$A$57,0)),0) -> 0.067567568 | G8: =D8*F8 -> 0.13513514
A9: Oaxaca Paloma | B9: Oaxaca Paloma | C9: Tequila blanco | D9: 1.5 | E9: =IFERROR(INDEX(Insumos!$F$5:$F$57,MATCH(C9,Insumos!$A$5:$A$57,0)),"?") -> oz | F9: =IFERROR(INDEX(Insumos!$H$5:$H$57,MATCH(C9,Insumos!$A$5:$A$57,0)),0) -> 0.78864353 | G9: =D9*F9 -> 1.1829653
A10: Oaxaca Paloma | B10: Oaxaca Paloma | C10: Jugo de toronja fresco | D10: 2 | E10: =IFERROR(INDEX(Insumos!$F$5:$F$57,MATCH(C10,Insumos!$A$5:$A$57,0)),"?") -> oz | F10: =IFERROR(INDEX(Insumos!$H$5:$H$57,MATCH(C10,Insumos!$A$5:$A$57,0)),0) -> 0.18 | G10: =D10*F10 -> 0.36
A11: Oaxaca Paloma | B11: Oaxaca Paloma | C11: Jugo de limón fresco | D11: 0.5 | E11: =IFERROR(INDEX(Insumos!$F$5:$F$57,MATCH(C11,Insumos!$A$5:$A$57,0)),"?") -> oz | F11: =IFERROR(INDEX(Insumos!$H$5:$H$57,MATCH(C11,Insumos!$A$5:$A$57,0)),0) -> 0.2 | G11: =D11*F11 -> 0.1
A12: Oaxaca Paloma | B12: Oaxaca Paloma | C12: Jarabe simple 1:1 | D12: 0.25 | E12: =IFERROR(INDEX(Insumos!$F$5:$F$57,MATCH(C12,Insumos!$A$5:$A$57,0)),"?") -> oz | F12: =IFERROR(INDEX(Insumos!$H$5:$H$57,MATCH(C12,Insumos!$A$5:$A$57,0)),0) -> 0.0256 | G12: =D12*F12 -> 0.0064
A13: Oaxaca Paloma | B13: Oaxaca Paloma | C13: Soda | D13: 2 | E13: =IFERROR(INDEX(Insumos!$F$5:$F$57,MATCH(C13,Insumos!$A$5:$A$57,0)),"?") -> oz | F13: =IFERROR(INDEX(Insumos!$H$5:$H$57,MATCH(C13,Insumos!$A$5:$A$57,0)),0) -> 0.024654832 | G13: =D13*F13 -> 0.049309665
A14: Oaxaca Paloma | B14: Oaxaca Paloma | C14: Borde de sal | D14: 1 | E14: =IFERROR(INDEX(Insumos!$F$5:$F$57,MATCH(C14,Insumos!$A$5:$A$57,0)),"?") -> unidad | F14: =IFERROR(INDEX(Insumos!$H$5:$H$57,MATCH(C14,Insumos!$A$5:$A$57,0)),0) -> 0.03 | G14: =D14*F14 -> 0.03
A15: Havana Maracuyá | B15: Havana Maracuyá | C15: Ron blanco | D15: 2 | E15: =IFERROR(INDEX(Insumos!$F$5:$F$57,MATCH(C15,Insumos!$A$5:$A$57,0)),"?") -> oz | F15: =IFERROR(INDEX(Insumos!$H$5:$H$57,MATCH(C15,Insumos!$A$5:$A$57,0)),0) -> 0.29585799 | G15: =D15*F15 -> 0.59171598
A16: Havana Maracuyá | B16: Havana Maracuyá | C16: Pulpa de maracuyá | D16: 1 | E16: =IFERROR(INDEX(Insumos!$F$5:$F$57,MATCH(C16,Insumos!$A$5:$A$57,0)),"?") -> oz | F16: =IFERROR(INDEX(Insumos!$H$5:$H$57,MATCH(C16,Insumos!$A$5:$A$57,0)),0) -> 0.14705882 | G16: =D16*F16 -> 0.14705882
... A153: Carajillo | B153: Carajillo | C153: Licor 43 | D153: 1.5 | E153: =IFERROR(INDEX(Insumos!$F$5:$F$57,MATCH(C153,Insumos!$A$5:$A$57,0)),"?") -> oz | F153: =IFERROR(INDEX(Insumos!$H$5:$H$57,MATCH(C153,Insumos!$A$5:$A$57,0)),0) -> 1.0252366 | G153: =D153*F153 -> 1.5378549
